{
  "url": "https://www.getverveai.com/blog/outsource-ecommerce",
  "title": "Outsource E-Commerce: A Beginner's Guide to Outsourcing.",
  "metaDescription": "Discover the benefits and risks of outsourcing e-commerce operations. Learn what services to delegate, when to outsource, and how to choose the right partner.",
  "canonical": "https://www.getverveai.com/blog/outsource-ecommerce",
  "h1": "Outsourcing E-Commerce: Benefits, Risks, and How to Choose the Right Partner",
  "headings": [
    {
      "level": "H1",
      "text": "Outsourcing E-Commerce: Benefits, Risks, and How to Choose the Right Partner"
    },
    {
      "level": "H2",
      "text": "What Is E-Commerce Outsourcing?"
    },
    {
      "level": "H2",
      "text": "Benefits of Outsourcing E-Commerce Operations"
    },
    {
      "level": "H3",
      "text": "1. Scalability"
    },
    {
      "level": "H3",
      "text": "2. Expertise"
    },
    {
      "level": "H3",
      "text": "3. Cost Efficiency"
    },
    {
      "level": "H3",
      "text": "4. Focus on Growth"
    },
    {
      "level": "H3",
      "text": "5. Technology Access"
    },
    {
      "level": "H1",
      "text": "More time, More Sales"
    },
    {
      "level": "H1",
      "text": "AI Forecasting For E-Commerce Merchants"
    },
    {
      "level": "H2",
      "text": "Risks and Challenges of Outsourcing"
    },
    {
      "level": "H2",
      "text": "How to Choose the Right Outsourcing Partner"
    },
    {
      "level": "H2",
      "text": "When Should You Outsource?"
    },
    {
      "level": "H2",
      "text": "The Future of E-Commerce Outsourcing"
    },
    {
      "level": "H2",
      "text": "Conclusion"
    },
    {
      "level": "H2",
      "text": "Related Reading"
    },
    {
      "level": "H1",
      "text": "Ditch CSV Exports and Excel Formulas"
    },
    {
      "level": "H1",
      "text": "AI Forecasting For Shopify Merchants"
    }
  ],
  "bodyText": "Outsourcing E-Commerce: Benefits, Risks, and How to Choose the Right Partner\n\nRunning an e-commerce business involves far more than setting up a storefront and marketing products. Behind every order are logistics, warehousing, fulfillment, customer service, and inventory management. For many growing retailers, handling these tasks in-house becomes overwhelming — that’s where outsourcing e-commerce operations comes in.\n\nIn this guide, we’ll break down what outsourcing means for e-commerce, the benefits and risks, and how to choose the right partner for your business.\n\nWhat Is E-Commerce Outsourcing?\n\nE-commerce outsourcing means delegating certain business functions to third-party providers. Instead of managing everything internally, businesses rely on partners with expertise, infrastructure, and technology to streamline operations.\n\nCommon areas of outsourcing include:\n\nLogistics & fulfillment – handled by third-party logistics (3PL) providers.\n\nWarehousing – outsourcing storage and stock management.\n\nCustomer service – support teams or call centers.\n\nAccounting/bookkeeping – financial tasks and reporting.\n\nDigital marketing – SEO, ads management, and content.\n\nSome companies outsource just one area (e.g., fulfillment), while others use end-to-end providers covering everything from warehousing to last-mile delivery.\n\nBenefits of Outsourcing E-Commerce Operations\n\nThe popularity of outsourcing has grown because of its many advantages.\n\n1. Scalability\n\nOutsourcing allows you to handle seasonal spikes in demand without expanding internal infrastructure.\n\n2. Expertise\n\nGain access to specialists in logistics, marketing, or customer service who bring experience and advanced tools.\n\n3. Cost Efficiency\n\nAvoid large capital investments in warehouses, vehicles, or staff. Outsourcing spreads costs across many clients.\n\n4. Focus on Growth\n\nBy reducing the operational burden, business owners can dedicate more time to product development and customer acquisition.\n\n5. Technology Access\n\nMany 3PLs provide order tracking systems, analytics dashboards, and API integrations with platforms like Shopify.\n\nMore time, More Sales\nAI Forecasting For E-Commerce Merchants\n\nForShopify\n\nFor WooCommerce\n\nRisks and Challenges of Outsourcing\n\nWhile outsourcing has benefits, it also comes with challenges to consider.\n\nLoss of control – less oversight on how orders are fulfilled or how customer service is delivered.\n\nBrand experience risk – poor third-party performance directly impacts customer trust.\n\nCosts – outsourcing fees may rise if order volumes are inconsistent.\n\nDependency – reliance on a single provider may create risks if they fail to deliver.\n\nBalancing these risks with clear agreements and careful partner selection is key.\n\nHow to Choose the Right Outsourcing Partner\n\nIf you decide outsourcing is right for you, choosing the right provider makes all the difference.\n\nKey steps include:\n\nDefine your needs – identify which areas (fulfillment, warehousing, customer service) to outsource.\n\nEvaluate providers – look at reliability, scalability, reputation, and pricing.\n\nCheck integration compatibility – ensure they work seamlessly with your e-commerce platform.\n\nService-Level Agreements (SLAs) – set clear expectations for delivery speed, accuracy, and return handling.\n\nWhen Should You Outsource?\n\nNot every business is ready to outsource. Signs that it might be time include:\n\nOrder volume is outgrowing your current capacity.\n\nStorage and fulfillment costs are rising rapidly.\n\nYou’re struggling to keep up with customer service.\n\nYou’re expanding into new markets or selling internationally.\n\nIf you’re facing these challenges, outsourcing could be the right next step.\n\nThe Future of E-Commerce Outsourcing\n\nThe outsourcing industry is evolving quickly. Key trends include:\n\nFull-service solutions – providers offering everything from warehousing to customer service.\n\nAutomation and AI – outsourced providers using robotics, predictive analytics, and automation to boost efficiency.\n\nGlobal logistics – the growing role of bonded warehouses for cross-border trade (see Bonded Inventory).\n\nForecasting technology – tools like Verve AI help businesses better predict demand, reducing reliance on excess outsourcing capacity.\n\nConclusion\n\nOutsourcing e-commerce operations can be a powerful strategy for growth. By leveraging external expertise, you can scale faster, save on costs, and focus on what matters most — your brand and customers.\n\nHowever, outsourcing isn’t without risks. Choosing the right partner and maintaining strong oversight are crucial to protecting your brand experience.\n\n👉 Pair outsourcing with smarter forecasting using Verve AI to balance efficiency, cost control, and growth.\n\nRelated Reading\n\nRetail & E-Commerce Operations\n\nObsolete Stock\n\nWhat is Bonded Inventory\n\nWhat is a KPI in Retail\n\nDitch CSV Exports and Excel Formulas\nAI Forecasting For Shopify Merchants\n\nFor Shopify\n\nFor WooCommerce\n\nAI Forecasting Software for E-Commerce Businesses\n\nQuick Links\n\nHome\n\nAbout\n\nPricing\n\nWhy Verve AI\n\nContact\n\nBlog\n\nTools\n\nImportant\n\nVerve AI Shopify\n\nVerve AI WooCommerce\n\nTwitter\n\nPrivacy Policy\n\nTerms\n\nFAQ\n\nGet in Touch\n\nHello@GetVerveAI.com\n\nCopyright © 2026 Verve AI. All rights reserved.",
  "bodyHtml": "",
  "images": [
    {
      "src": "https://framerusercontent.com/images/zplhvSQDvA45ptNBhwmtoWBGiU0.png?width=940&height=469",
      "alt": "Verve AI Forecasting Software Logo"
    },
    {
      "src": "https://framerusercontent.com/images/zplhvSQDvA45ptNBhwmtoWBGiU0.png",
      "alt": "Verve AI Forecasting Software Logo"
    },
    {
      "src": "https://api.producthunt.com/widgets/embed-image/v1/featured.svg?post_id=1001054&theme=light&t=1754230295937",
      "alt": "Verve AI - AI Forecasting for Shopify - AI Forecasting, quick and easy, no spreadsheets required | Product Hunt"
    },
    {
      "src": "https://fazier.com/api/v1//public/badges/launch_badges.svg?badge_type=featured&theme=dark",
      "alt": "Fazier badge"
    },
    {
      "src": "https://twelve.tools/badge0-white.svg",
      "alt": "Featured on Twelve Tools"
    }
  ],
  "internalLinks": [],
  "externalLinks": [],
  "jsonLd": [],
  "scrapedAt": "2026-04-19T13:41:42.813Z",
  "htmlContent": "<h1>Outsourcing E-Commerce: Benefits, Risks, and How to Choose the Right Partner</h1><p>Running an e-commerce business involves far more than setting up a storefront and marketing products. Behind every order are logistics, warehousing, fulfillment, customer service, and inventory management. For many growing retailers, handling these tasks in-house becomes overwhelming — that’s where <strong>outsourcing e-commerce operations</strong> comes in.</p><p>In this guide, we’ll break down what outsourcing means for e-commerce, the benefits and risks, and how to choose the right partner for your business.</p><h2>What Is E-Commerce Outsourcing?</h2><p>E-commerce outsourcing means delegating certain business functions to third-party providers. Instead of managing everything internally, businesses rely on partners with expertise, infrastructure, and technology to streamline operations.</p><p><strong>Common areas of outsourcing include:</strong></p><ul><li data-preset-tag=\"p\"><p><strong>Logistics &amp; fulfillment</strong> – handled by third-party logistics (3PL) providers.</p></li><li data-preset-tag=\"p\"><p><strong>Warehousing</strong> – outsourcing storage and stock management.</p></li><li data-preset-tag=\"p\"><p><strong>Customer service</strong> – support teams or call centers.</p></li><li data-preset-tag=\"p\"><p><strong>Accounting/bookkeeping</strong> – financial tasks and reporting.</p></li><li data-preset-tag=\"p\"><p><strong>Digital marketing</strong> – SEO, ads management, and content.</p></li></ul><p>Some companies outsource just one area (e.g., fulfillment), while others use <strong>end-to-end providers</strong> covering everything from warehousing to last-mile delivery.</p><h2>Benefits of Outsourcing E-Commerce Operations</h2><p>The popularity of outsourcing has grown because of its many advantages.</p><h3>1. Scalability</h3><p>Outsourcing allows you to handle seasonal spikes in demand without expanding internal infrastructure.</p><h3>2. Expertise</h3><p>Gain access to specialists in logistics, marketing, or customer service who bring experience and advanced tools.</p><h3>3. Cost Efficiency</h3><p>Avoid large capital investments in warehouses, vehicles, or staff. Outsourcing spreads costs across many clients.</p><h3>4. Focus on Growth</h3><p>By reducing the operational burden, business owners can dedicate more time to product development and customer acquisition.</p><h3>5. Technology Access</h3><p>Many 3PLs provide order tracking systems, analytics dashboards, and API integrations with platforms like Shopify.</p>\n<h2>Risks and Challenges of Outsourcing</h2><p>While outsourcing has benefits, it also comes with challenges to consider.</p><ul><li data-preset-tag=\"p\"><p><strong>Loss of control</strong> – less oversight on how orders are fulfilled or how customer service is delivered.</p></li><li data-preset-tag=\"p\"><p><strong>Brand experience risk</strong> – poor third-party performance directly impacts customer trust.</p></li><li data-preset-tag=\"p\"><p><strong>Costs</strong> – outsourcing fees may rise if order volumes are inconsistent.</p></li><li data-preset-tag=\"p\"><p><strong>Dependency</strong> – reliance on a single provider may create risks if they fail to deliver.</p></li></ul><p>Balancing these risks with clear agreements and careful partner selection is key.</p><h2>How to Choose the Right Outsourcing Partner</h2><p>If you decide outsourcing is right for you, choosing the right provider makes all the difference.</p><p><strong>Key steps include:</strong></p><ul><li data-preset-tag=\"p\"><p><strong>Define your needs</strong> – identify which areas (fulfillment, warehousing, customer service) to outsource.</p></li><li data-preset-tag=\"p\"><p><strong>Evaluate providers</strong> – look at reliability, scalability, reputation, and pricing.</p></li><li data-preset-tag=\"p\"><p><strong>Check integration compatibility</strong> – ensure they work seamlessly with your e-commerce platform.</p></li><li data-preset-tag=\"p\"><p><strong>Service-Level Agreements (SLAs)</strong> – set clear expectations for delivery speed, accuracy, and return handling.</p></li></ul><h2>When Should You Outsource?</h2><p>Not every business is ready to outsource. Signs that it might be time include:</p><ul><li data-preset-tag=\"p\"><p>Order volume is outgrowing your current capacity.</p></li><li data-preset-tag=\"p\"><p>Storage and fulfillment costs are rising rapidly.</p></li><li data-preset-tag=\"p\"><p>You’re struggling to keep up with customer service.</p></li><li data-preset-tag=\"p\"><p>You’re expanding into new markets or selling internationally.</p></li></ul><p>If you’re facing these challenges, outsourcing could be the right next step.</p><h2>The Future of E-Commerce Outsourcing</h2><p>The outsourcing industry is evolving quickly. Key trends include:</p><ul><li data-preset-tag=\"p\"><p><strong>Full-service solutions</strong> – providers offering everything from warehousing to customer service.</p></li><li data-preset-tag=\"p\"><p><strong>Automation and AI</strong> – outsourced providers using robotics, predictive analytics, and automation to boost efficiency.</p></li><li data-preset-tag=\"p\"><p><strong>Global logistics</strong> – the growing role of bonded warehouses for cross-border trade (see <a href=\"/blog/what-is-bonded-inventory\">Bonded Inventory</a>).</p></li><li data-preset-tag=\"p\"><p><strong>Forecasting technology</strong> – tools like <a href=\"https://app.getverveai.com/\">Verve AI</a> help businesses better predict demand, reducing reliance on excess outsourcing capacity.</p></li></ul><h2>Conclusion</h2><p>Outsourcing e-commerce operations can be a powerful strategy for growth. By leveraging external expertise, you can scale faster, save on costs, and focus on what matters most — your brand and customers.</p><p>However, outsourcing isn’t without risks. Choosing the right partner and maintaining strong oversight are crucial to protecting your brand experience.</p><p>👉 Pair outsourcing with smarter forecasting using <a href=\"https://app.getverveai.com/\">Verve AI</a> to balance efficiency, cost control, and growth.</p><h2>Related Reading</h2><ul><li data-preset-tag=\"p\"><p><a href=\"/blog/retail-e-commerce-operations\">Retail &amp; E-Commerce Operations</a></p></li><li data-preset-tag=\"p\"><p><a href=\"/blog/obsolete-stock\">Obsolete Stock</a></p></li><li data-preset-tag=\"p\"><p><a href=\"/blog/what-is-bonded-inventory\">What is Bonded Inventory</a></p></li><li data-preset-tag=\"p\"><p><a href=\"/blog/what-is-a-kpi-retail\">What is a KPI in Retail</a></p></li></ul>",
  "imageUrl": "https://framerusercontent.com/images/44Mnvfqp4m5Af5VXs9aqr7EpzNY.png",
  "imageAlt": "Outsource Ecommerce Know All Your Options",
  "csvDate": "2025-08-28T21:31:04.785Z"
}