{
  "url": "https://www.getverveai.com/tools/reorder-point-calculator",
  "title": "Reorder Point Calculator: Free Interactive Tool + Formula Guide",
  "metaDescription": "Calculate your reorder point instantly. Enter average daily demand, lead time, and safety stock — get your ROP and days until reorder in seconds. Free interactive tool.",
  "canonical": "https://www.getverveai.com/tools/reorder-point-calculator",
  "h1": "Reorder Point Calculator",
  "headings": [
    { "level": "H1", "text": "Reorder Point Calculator" },
    { "level": "H2", "text": "What Is a Reorder Point?" },
    { "level": "H2", "text": "The Reorder Point Formula" },
    { "level": "H2", "text": "Use the Free Calculator Below" },
    { "level": "H2", "text": "Step-by-Step Example" },
    { "level": "H2", "text": "When to Update Your Reorder Points" },
    { "level": "H2", "text": "Why Lead Time and Safety Stock Both Matter" },
    { "level": "H2", "text": "Frequently Asked Questions" }
  ],
  "htmlContent": "<h1>Reorder Point Calculator</h1>\n\n<p>Ordering too late causes stockouts. Ordering too early ties up cash. The reorder point is the number that keeps you in between — the exact inventory level at which you should place your next purchase order so stock arrives before you run out. This free interactive calculator gives you that number instantly, based on your actual demand and lead time data.</p>\n\n<h2>What Is a Reorder Point?</h2>\n\n<p>A reorder point (ROP) is the stock level that triggers a new purchase order. When your on-hand inventory falls to this level, you place an order — and by the time that order arrives (after your supplier's lead time), you still have stock left. Without a defined reorder point, you're either ordering by gut feel or reacting to near-stockouts.</p>\n\n<p>Reorder points matter most for fast-moving SKUs and products with long or variable lead times. A product that sells 5 units per day and takes 14 days to arrive needs a very different reorder point than one that sells 50 units per day and ships in 2 days.</p>\n\n<p>Getting this wrong has real costs. Stockouts lose you the sale and often the customer. Excess inventory means tied-up working capital, higher storage costs, and the risk of dead stock if demand shifts.</p>\n\n<h2>The Reorder Point Formula</h2>\n\n<p>The standard formula used by inventory planners is:</p>\n\n<p><strong>Reorder Point = (Average Daily Demand × Lead Time) + Safety Stock</strong></p>\n\n<p>Where:</p>\n<ul>\n<li><strong>Average Daily Demand</strong> — the number of units you sell per day on average (use the last 30–60 days for best accuracy)</li>\n<li><strong>Lead Time</strong> — the number of days between placing a purchase order and receiving the goods at your warehouse</li>\n<li><strong>Safety Stock</strong> — a buffer to absorb demand spikes and supplier delays (enter 0 if you have none, but most merchants should carry some)</li>\n</ul>\n\n<p>The result tells you: when your stock drops to this number, it is time to reorder. You can also enter your current stock level to see how many days you have left before you hit your reorder point.</p>\n\n<h2>Use the Free Calculator Below</h2>\n\n<p>Enter your average daily demand, supplier lead time, and safety stock. Optionally add your current stock level to see days until reorder. The calculator updates instantly as you type.</p>\n\n<p>If you are unsure of your average daily demand, export the last 30 days of sales from Shopify and divide total units sold by 30. For safety stock, use our <a href=\"https://www.getverveai.com/blog/safety-stock-calculator\">free safety stock calculator</a> to calculate the right buffer for each SKU.</p>\n\n<h2>Step-by-Step Example</h2>\n\n<p>Here is a worked example for a Shopify merchant selling a mid-velocity product:</p>\n\n<ul>\n<li><strong>Average daily demand:</strong> 20 units/day</li>\n<li><strong>Lead time:</strong> 10 days</li>\n<li><strong>Safety stock:</strong> 50 units</li>\n<li><strong>Current stock:</strong> 350 units</li>\n</ul>\n\n<p><strong>Step 1 — Reorder Point:</strong> (20 × 10) + 50 = <strong>250 units</strong></p>\n<p><strong>Step 2 — Days until reorder:</strong> (350 − 250) ÷ 20 = <strong>5 days</strong></p>\n\n<p>This means: set an alert at 250 units. With 350 units on hand today, you have roughly 5 days before you need to place a new order. When stock hits 250, your supplier has enough lead time to deliver before you run out — including the 50-unit safety buffer.</p>\n\n<h2>When to Update Your Reorder Points</h2>\n\n<p>Reorder points go stale. Recalculate whenever any of these change:</p>\n\n<ul>\n<li><strong>Demand shifts</strong> — a product enters a growth phase, seasonality kicks in, or a promotion drives a lasting uplift. Your 30-day average will catch this if you recalculate regularly.</li>\n<li><strong>Lead time changes</strong> — a new supplier, a change in shipping route, or supply chain disruption. Even a 2-day increase in lead time can shift your ROP significantly on fast-moving SKUs.</li>\n<li><strong>Safety stock changes</strong> — if you've recalculated your safety stock levels, your reorder points need updating too since ROP is built on top of safety stock.</li>\n<li><strong>New product launches</strong> — use conservative estimates for average demand until you have 30+ days of data.</li>\n</ul>\n\n<p>A practical cadence: review reorder points monthly for your top 20% of SKUs by revenue, and quarterly for the rest.</p>\n\n<h2>Why Lead Time and Safety Stock Both Matter</h2>\n\n<p>Lead time and safety stock are the two biggest levers in your reorder point. Understanding how they interact helps you make better stocking decisions:</p>\n\n<ul>\n<li><strong>Longer lead time → higher ROP.</strong> If your supplier takes 21 days instead of 7, you need to hold 3× more demand coverage before reordering. Shortening lead times (closer suppliers, faster shipping) directly reduces working capital requirements.</li>\n<li><strong>Higher demand variability → higher safety stock → higher ROP.</strong> Products with predictable, steady demand need less safety stock than volatile ones. Use the standard deviation of daily demand to size safety stock properly.</li>\n<li><strong>Zero safety stock is a choice, not a default.</strong> Some merchants run zero safety stock on slow-moving or low-margin items where holding cost exceeds stockout cost. That is a valid trade-off — but it should be deliberate.</li>\n</ul>\n\n<p>For a deeper dive on sizing safety stock correctly, see our <a href=\"https://www.getverveai.com/blog/safety-stock-calculator\">safety stock calculator and formula guide</a>.</p>\n\n<h2>Frequently Asked Questions</h2>\n\n<h3>What is a good reorder point?</h3>\n<p>There is no universal number — it depends entirely on your demand rate, lead time, and safety stock. The formula above gives you a statistically grounded ROP for your specific situation. Use it per-SKU rather than applying a blanket rule across your catalogue.</p>\n\n<h3>What if my lead time varies?</h3>\n<p>Use your average lead time for the base calculation, and fold lead time variability into your safety stock instead. Our <a href=\"https://www.getverveai.com/blog/safety-stock-calculator\">safety stock calculator</a> uses the standard deviation of demand to size the buffer — this implicitly handles some lead time variability as well.</p>\n\n<h3>Should I include safety stock in my reorder point?</h3>\n<p>Yes, almost always. Safety stock without a properly set reorder point is useless — you will dip into it on every replenishment cycle. The reorder point formula already accounts for safety stock by adding it on top of the demand-during-lead-time figure.</p>\n\n<h3>How often should I recalculate reorder points?</h3>\n<p>Monthly for top SKUs, quarterly for everything else. If you have a large catalogue, automate the calculation in your inventory system or use Verve AI to recalculate continuously based on live Shopify data.</p>\n\n<h3>Can I use this for multiple SKUs?</h3>\n<p>The calculator is designed for one SKU at a time — run it for each product separately. For large catalogues, consider our <a href=\"https://www.getverveai.com/blog/demand-forecasting-excel\">free demand forecasting Excel template</a> which includes a multi-SKU reorder point table.</p>",
  "bodyHtml": "",
  "bodyText": "",
  "images": [],
  "internalLinks": [],
  "externalLinks": [],
  "jsonLd": [],
  "scrapedAt": "2026-04-23T00:00:00.000Z",
  "imageUrl": "",
  "imageAlt": "",
  "csvDate": "2026-04-23T00:00:00.000Z"
}
